datahub_test_bed/__init__.py
datahub_test_bed/__main__.py
datahub_test_bed/cli/__init__.py
datahub_test_bed/cli/main.py
datahub_test_bed/validations/__init__.py
datahub_test_bed/validations/exceptions.py
datahub_test_bed/validations/models.py
datahub_test_bed/validations/utils.py
datahub_test_bed/validations/storage/__init__.py
datahub_test_bed/validations/storage/client.py
datahub_test_bed/validations/storage/main.py
datahub_test_bed-1.0.0.dist-info/licenses/LICENSE
datahub_test_bed-1.0.0.dist-info/METADATA
datahub_test_bed-1.0.0.dist-info/WHEEL
datahub_test_bed-1.0.0.dist-info/entry_points.txt
datahub_test_bed-1.0.0.dist-info/top_level.txt
datahub_test_bed-1.0.0.dist-info/RECORD
