Metadata-Version: 2.4
Name: datahub_test_bed
Version: 1.0.0
Summary: GHGA's utility tool for technical validation of Data Hubs and benchmarks
Author-email: "German Human Genome Phenome Archive (GHGA)" <contact@ghga.de>
License: Apache 2.0
Project-URL: Repository, https://github.com/ghga-de/datahub-test-bed
Classifier: Development Status :: 1 - Planning
Classifier: Operating System :: POSIX :: Linux
Classifier: Programming Language :: Python :: 3
Classifier: Programming Language :: Python :: 3.12
Classifier: License :: OSI Approved :: Apache Software License
Classifier: Topic :: Internet :: WWW/HTTP :: HTTP Servers
Classifier: Topic :: Software Development :: Libraries
Classifier: Intended Audience :: Developers
Requires-Python: >=3.12
License-File: LICENSE
Requires-Dist: boto3<2,>=1.37.0
Requires-Dist: botocore<2,>=1.37.0
Requires-Dist: pydantic<3,>=2
Requires-Dist: pydantic_settings<3,>=2
Requires-Dist: PyYAML<7,>=6
Requires-Dist: typer~=0.15
Dynamic: license-file
